[[{"__type__":"cc.Prefab","_name":"DailyGiftWindow","data":{"__id__":1}},{"__type__":"cc.Node","_name":"DailyGiftWindow","_children":[{"__id__":2},{"__id__":3},{"__id__":4},{"__id__":5},{"__id__":6},{"__id__":13}],"_components":[{"__type__":"cc.Widget","node":{"__id__":1},"_alignFlags":45},{"__type__":"cc.BlockInputEvents","node":{"__id__":1}},{"__type__":"ab07caimcBCU4o6q3WJp0e+","node":{"__id__":1},"sunNode":{"__id__":7},"rewardPic":{"__id__":9},"rewardPic2":{"__id__":11},"tripleRewardBtn":{"__id__":4},"tripleRewardBtnFree":{"__id__":5},"rewardBtn":{"__id__":3}}],"_prefab":{"__type__":"cc.PrefabInfo","root":{"__id__":1},"asset":{"__uuid__":"2e+8xtbi5Mm56Zis9DIQ8d"},"fileId":"4eC23cAT9P/q3T5Bg8Z9Bb"},"_contentSize":{"__type__":"cc.Size","width":720,"height":1280},"_trs":{"__type__":"TypedArray","ctor":"Float64Array","array":[360,640,0,0,0,0,1,1,1,1]}},{"__type__":"cc.Node","_name":"New Sprite(Splash)","_parent":{"__id__":1},"_components":[{"__type__":"cc.Sprite","node":{"__id__":2},"_materials":[{"__uuid__":"ecpdLyjvZBwrvm+cedCcQy"}],"_spriteFrame":{"__uuid__":"a2MjXRFdtLlYQ5ouAFv/+R"},"_sizeMode":0},{"__type__":"cc.Widget","node":{"__id__":2},"_alignFlags":45,"_originalWidth":100,"_originalHeight":100}],"_prefab":{"__type__":"cc.PrefabInfo","root":{"__id__":1},"asset":{"__uuid__":"2e+8xtbi5Mm56Zis9DIQ8d"},"fileId":"85n7E7GQNNq7rXm++EkKa+"},"_opacity":180,"_color":{"__type__":"cc.Color"},"_contentSize":{"__type__":"cc.Size","width":720,"height":1280},"_trs":{"__type__":"TypedArray","ctor":"Float64Array","array":[0,0,0,0,0,0,1,1,1,1]}},{"__type__":"cc.Node","_name":"collectBtn","_parent":{"__id__":1},"_components":[{"__type__":"cc.Sprite","node":{"__id__":3},"_materials":[{"__uuid__":"ecpdLyjvZBwrvm+cedCcQy"}],"_spriteFrame":{"__uuid__":"7ajGSP2iBHZpaetlLb92Yn"}},{"__type__":"cc.Button","node":{"__id__":3},"_normalMaterial":{"__uuid__":"ecpdLyjvZBwrvm+cedCcQy"},"clickEvents":[{"__type__":"cc.ClickEvent","target":{"__id__":1},"_componentId":"ab07caimcBCU4o6q3WJp0e+","handler":"onCollectBtn"}],"_N$transition":3,"transition":3},{"__type__":"cc.Widget","node":{"__id__":3},"_alignFlags":18,"_verticalCenter":-460.357}],"_prefab":{"__type__":"cc.PrefabInfo","root":{"__id__":1},"asset":{"__uuid__":"2e+8xtbi5Mm56Zis9DIQ8d"},"fileId":"59n+qAz5FPqr9WmBzmvA49"},"_contentSize":{"__type__":"cc.Size","width":176,"height":46},"_trs":{"__type__":"TypedArray","ctor":"Float64Array","array":[0,-460.357,0,0,0,0,1,1,1,1]}},{"__type__":"cc.Node","_name":"tripleCollectBtn","_parent":{"__id__":1},"_components":[{"__type__":"cc.Sprite","node":{"__id__":4},"_materials":[{"__uuid__":"ecpdLyjvZBwrvm+cedCcQy"}],"_spriteFrame":{"__uuid__":"b0/26MSYtDBKBZu7jxU4OF"}},{"__type__":"cc.Button","node":{"__id__":4},"clickEvents":[{"__type__":"cc.ClickEvent","target":{"__id__":1},"_componentId":"ab07caimcBCU4o6q3WJp0e+","handler":"onTripleCollectBtn"}]},{"__type__":"cc.Widget","node":{"__id__":4},"_alignFlags":18,"_verticalCenter":-328.287}],"_prefab":{"__type__":"cc.PrefabInfo","root":{"__id__":1},"asset":{"__uuid__":"2e+8xtbi5Mm56Zis9DIQ8d"},"fileId":"dc4fiefERL/b2ovllqkwqT"},"_contentSize":{"__type__":"cc.Size","width":337,"height":98},"_trs":{"__type__":"TypedArray","ctor":"Float64Array","array":[0,-328.287,0,0,0,0,1,1,1,1]}},{"__type__":"cc.Node","_name":"tripleCollectBtnFree","_parent":{"__id__":1},"_components":[{"__type__":"cc.Sprite","node":{"__id__":5},"_materials":[{"__uuid__":"ecpdLyjvZBwrvm+cedCcQy"}],"_spriteFrame":{"__uuid__":"a4t1MCyvlIPabKt15Wqadb"}},{"__type__":"cc.Button","node":{"__id__":5},"clickEvents":[{"__type__":"cc.ClickEvent","target":{"__id__":1},"_componentId":"ab07caimcBCU4o6q3WJp0e+","handler":"onTripleCollectBtn"}]},{"__type__":"cc.Widget","node":{"__id__":5},"_alignFlags":18,"_verticalCenter":-328.287}],"_prefab":{"__type__":"cc.PrefabInfo","root":{"__id__":1},"asset":{"__uuid__":"2e+8xtbi5Mm56Zis9DIQ8d"},"fileId":"fa85qMtsVC8JoLItySFAWa"},"_contentSize":{"__type__":"cc.Size","width":348,"height":113},"_trs":{"__type__":"TypedArray","ctor":"Float64Array","array":[0,-328.287,0,0,0,0,1,1,1,1]}},{"__type__":"cc.Node","_name":"gift","_parent":{"__id__":1},"_children":[{"__id__":7},{"__id__":8}],"_components":[{"__type__":"cc.Widget","node":{"__id__":6}}],"_prefab":{"__type__":"cc.PrefabInfo","root":{"__id__":1},"asset":{"__uuid__":"2e+8xtbi5Mm56Zis9DIQ8d"},"fileId":"3bag7k2v1LR5Qpug1coWRH"},"_trs":{"__type__":"TypedArray","ctor":"Float64Array","array":[0,-253.168,0,0,0,0,1,1,1,1]}},{"__type__":"cc.Node","_name":"gk_01","_parent":{"__id__":6},"_components":[{"__type__":"cc.Sprite","node":{"__id__":7},"_materials":[{"__uuid__":"ecpdLyjvZBwrvm+cedCcQy"}],"_spriteFrame":{"__uuid__":"c7nOsROIxEiKr/qWqCi6Lz"},"_sizeMode":0},{"__type__":"cc.Widget","node":{"__id__":7},"_alignFlags":18,"_verticalCenter":305.939,"_horizontalCenter":-9.135}],"_prefab":{"__type__":"cc.PrefabInfo","root":{"__id__":1},"asset":{"__uuid__":"2e+8xtbi5Mm56Zis9DIQ8d"},"fileId":"1d65iknU1JxpvY+eLhjUQ3"},"_contentSize":{"__type__":"cc.Size","width":500,"height":500},"_trs":{"__type__":"TypedArray","ctor":"Float64Array","array":[-9.135,305.939,0,0,0,0,1,1,1,1]}},{"__type__":"cc.Node","_name":"New Layout","_parent":{"__id__":6},"_children":[{"__id__":9},{"__id__":11}],"_components":[{"__type__":"cc.Sprite","node":{"__id__":8},"_materials":[{"__uuid__":"ecpdLyjvZBwrvm+cedCcQy"}],"_type":1,"_sizeMode":0},{"__type__":"cc.Layout","node":{"__id__":8},"_layoutSize":{"__type__":"cc.Size","width":356,"height":50.4},"_resize":1,"_N$layoutType":1,"_N$spacingX":80},{"__type__":"cc.Widget","node":{"__id__":8},"_alignFlags":18,"_verticalCenter":305.93899999999996,"_horizontalCenter":1.8050000000000015}],"_prefab":{"__type__":"cc.PrefabInfo","root":{"__id__":1},"asset":{"__uuid__":"2e+8xtbi5Mm56Zis9DIQ8d"},"fileId":"acsEyLAZtGJb+DpsbfkwFx"},"_contentSize":{"__type__":"cc.Size","width":356,"height":50.4},"_anchorPoint":{"__type__":"cc.Vec2","x":0.73,"y":-6.51},"_trs":{"__type__":"TypedArray","ctor":"Float64Array","array":[83.685,-47.36500000000001,0,0,0,0,1,1,1,1]}},{"__type__":"cc.Node","_name":"rewardPic","_parent":{"__id__":8},"_children":[{"__id__":10}],"_components":[{"__type__":"cc.Sprite","node":{"__id__":9},"_materials":[{"__uuid__":"ecpdLyjvZBwrvm+cedCcQy"}],"_spriteFrame":{"__uuid__":"67tbCCYRpBkoJ0W76HQ5py"}}],"_prefab":{"__type__":"cc.PrefabInfo","root":{"__id__":1},"asset":{"__uuid__":"2e+8xtbi5Mm56Zis9DIQ8d"},"fileId":"4a/VP7gPpCdbkYTkOZW6yB"},"_contentSize":{"__type__":"cc.Size","width":138,"height":138},"_trs":{"__type__":"TypedArray","ctor":"Float64Array","array":[-190.88,353.509,0,0,0,0,1,1,1,1]}},{"__type__":"cc.Node","_name":"rewardNum","_parent":{"__id__":9},"_components":[{"__type__":"cc.Label","node":{"__id__":10},"_materials":[{"__uuid__":"ecpdLyjvZBwrvm+cedCcQy"}],"_useOriginalSize":false,"_string":"X1","_N$string":"X1","_fontSize":80,"_lineHeight":80,"_N$file":{"__uuid__":"1aJRvHLhlP051VBOq4ear2"},"_isSystemFontUsed":false,"_N$horizontalAlign":1,"_N$verticalAlign":1},{"__type__":"cc.Widget","node":{"__id__":10}}],"_prefab":{"__type__":"cc.PrefabInfo","root":{"__id__":1},"asset":{"__uuid__":"2e+8xtbi5Mm56Zis9DIQ8d"},"fileId":"feSoohJgFIOZDhWCv7HNba"},"_color":{"__type__":"cc.Color","r":133,"g":119,"b":35},"_contentSize":{"__type__":"cc.Size","width":102.46,"height":100.8},"_trs":{"__type__":"TypedArray","ctor":"Float64Array","array":[113.716,12.097,0,0,0,0,1,0.8,0.8,1]}},{"__type__":"cc.Node","_name":"rewardPic2","_parent":{"__id__":8},"_children":[{"__id__":12}],"_components":[{"__type__":"cc.Sprite","node":{"__id__":11},"_materials":[{"__uuid__":"ecpdLyjvZBwrvm+cedCcQy"}],"_spriteFrame":{"__uuid__":"67tbCCYRpBkoJ0W76HQ5py"}}],"_prefab":{"__type__":"cc.PrefabInfo","root":{"__id__":1},"asset":{"__uuid__":"2e+8xtbi5Mm56Zis9DIQ8d"},"fileId":"b8ZwBNg+1Ava1YEKWLrs7V"},"_contentSize":{"__type__":"cc.Size","width":138,"height":138},"_trs":{"__type__":"TypedArray","ctor":"Float64Array","array":[27.120000000000005,353.509,0,0,0,0,1,1,1,1]}},{"__type__":"cc.Node","_name":"rewardNum","_parent":{"__id__":11},"_components":[{"__type__":"cc.Label","node":{"__id__":12},"_materials":[{"__uuid__":"ecpdLyjvZBwrvm+cedCcQy"}],"_useOriginalSize":false,"_string":"X1","_N$string":"X1","_fontSize":80,"_lineHeight":80,"_N$file":{"__uuid__":"1aJRvHLhlP051VBOq4ear2"},"_isSystemFontUsed":false,"_N$horizontalAlign":1,"_N$verticalAlign":1},{"__type__":"cc.Widget","node":{"__id__":12}}],"_prefab":{"__type__":"cc.PrefabInfo","root":{"__id__":1},"asset":{"__uuid__":"2e+8xtbi5Mm56Zis9DIQ8d"},"fileId":"2aTSP0wlVBw4wNhh7eO81x"},"_color":{"__type__":"cc.Color","r":255,"g":244,"b":174},"_contentSize":{"__type__":"cc.Size","width":102.46,"height":100.8},"_trs":{"__type__":"TypedArray","ctor":"Float64Array","array":[112.737,11,0,0,0,0,1,0.8,0.8,1]}},{"__type__":"cc.Node","_name":"qd_05","_parent":{"__id__":1},"_components":[{"__type__":"cc.Sprite","node":{"__id__":13},"_materials":[{"__uuid__":"ecpdLyjvZBwrvm+cedCcQy"}],"_spriteFrame":{"__uuid__":"46XgSRsB5ACZbcjGKemZr5"}},{"__type__":"cc.Widget","node":{"__id__":13},"_alignFlags":18,"_verticalCenter":394.248}],"_prefab":{"__type__":"cc.PrefabInfo","root":{"__id__":1},"asset":{"__uuid__":"2e+8xtbi5Mm56Zis9DIQ8d"},"fileId":"ccvxPhboRHpbPu6dRpH4Ah"},"_contentSize":{"__type__":"cc.Size","width":430,"height":113},"_trs":{"__type__":"TypedArray","ctor":"Float64Array","array":[0,394.248,0,0,0,0,1,1,1,1]}}],{"__type__":"cc.SpriteFrame","content":{"name":"qd_05","texture":"d3l4silgpNC4FGbh8MqOcG","rect":[0,0,430,113],"offset":[0,0],"originalSize":[430,113],"capInsets":[0,0,0,0]}},{"__type__":"cc.SpriteFrame","content":{"name":"yx_btn_gw","texture":"6cpPvt0aVNWIHDsLgx6QBU","rect":[0,0,137,136],"offset":[0,0],"originalSize":[137,136],"capInsets":[0,0,0,0]}},{"__type__":"cc.SpriteFrame","content":{"name":"X1","texture":"2a3Mh4XchBj5b2VWyDPVFg","rect":[83,31,176,46],"offset":[-3,2.5],"originalSize":[348,113],"capInsets":[0,0,0,0]}},{"__type__":"cc.SpriteFrame","content":{"name":"default_sprite_splash","texture":"02delMVqdBD70a/HSD99FK","rect":[0,0,2,2],"offset":[0,0],"originalSize":[2,2],"capInsets":[0,0,0,0]}},{"__type__":"cc.SpriteFrame","content":{"name":"3","texture":"25LSTgXBtD8YjiGmJOavmx","rect":[0,0,348,113],"offset":[0,0],"originalSize":[348,113],"capInsets":[0,0,0,0]}},{"__type__":"cc.SpriteFrame","content":{"name":"qd_07","texture":"7bpx8mCCZIvpnShH0PRTR9","rect":[0,0,337,98],"offset":[0,0],"originalSize":[337,98],"capInsets":[0,0,0,0]}},{"__type__":"cc.SpriteFrame","content":{"name":"qd_06","texture":"71FsRhdL5J4qKazOQuRuXR","rect":[0,0,530,542],"offset":[0,0],"originalSize":[530,542],"capInsets":[0,0,0,0]}}]